[
  {
    "id": "1",
    "info": "one"
  },
  {
    "id": "2",
    "info": "two"
  },
  {
    "id": "3",
    "info": "three"
  },
  {
    "id": "4",
    "info": "four"
  },
  {
    "id": "5",
    "info": "five"
  },
  {
    "id": "6",
    "info": "six"
  },
  {
    "id": "7",
    "info": "seven"
  },
  {
    "id": "8",
    "info": "eight"
  },
  {
    "id": "9",
    "info": "none"
  },
  {
    "id": "10",
    "info": "ten"
  },
  {
    "id": "11",
    "info": "eleven"
  },
  {
    "id": "12",
    "info": "twelve"
  },
  {
    "id": "13",
    "info": "thirteen"
  },
  {
    "id": "14",
    "info": "fourteen"
  },
  {
    "id": "15",
    "info": "fifteen"
  },
  {
    "id": "16",
    "info": "sixteen"
  },
  {
    "id": "17",
    "info": "seventeen"
  },
  {
    "id": "18",
    "info": "eighteen"
  },
  {
    "id": "19",
    "info": "nineteen"
  },
  {
    "id": "20",
    "info": "twenty"
  },
  {
    "id": "21",
    "info": "twenty one"
  },
  {
    "id": "22",
    "info": "twenty two"
  },
  {
    "id": "23",
    "info": "twenty three"
  },
  {
    "id": "24",
    "info": "twenty four"
  },
  {
    "id": "25",
    "info": "twenty five"
  },
  {
    "id": "26",
    "info": "twenty six"
  },
  {
    "id": "27",
    "info": "twenty seven"
  },
  {
    "id": "28",
    "info": "twenty eight"
  },
  {
    "id": "29",
    "info": "twenty nine"
  },
  {
    "id": "30",
    "info": "thirty"
  },
  {
    "id": "31",
    "info": "thirtyone"
  },
  {
    "id": "32",
    "info": "thirtytwo"
  },
  {
    "id": "33",
    "info": "thirtythree"
  },
  {
    "id": "34",
    "info": "thirtyfour"
  },
  {
    "id": "35",
    "info": "thirtyfive"
  },
  {
    "id": "36",
    "info": "thirtysix"
  },
  {
    "id": "37",
    "info": "thirtyseven"
  },
  {
    "id": "35",
    "info": "thirtyfive"
  },
  {
    "id": "36",
    "info": "thirtysix"
  },
  {
    "id": "37",
    "info": "thirtyseven"
  },
  {
    "id": "1",
    "info": "one"
  },
  {
    "id": "2",
    "info": "two"
  },
  {
    "id": "3",
    "info": "three"
  },
  {
    "id": "4",
    "info": "four"
  },
  {
    "id": "5",
    "info": "five"
  },
  {
    "id": "6",
    "info": "six"
  },
  {
    "id": "7",
    "info": "seven"
  },
  {
    "id": "8",
    "info": "eight"
  },
  {
    "id": "9",
    "info": "none"
  },
  {
    "id": "10",
    "info": "ten"
  },
  {
    "id": "11",
    "info": "eleven"
  },
  {
    "id": "12",
    "info": "twelve"
  },
  {
    "id": "13",
    "info": "thirteen"
  },
  {
    "id": "14",
    "info": "fourteen"
  },
  {
    "id": "15",
    "info": "fifteen"
  },
  {
    "id": "16",
    "info": "sixteen"
  },
  {
    "id": "17",
    "info": "seventeen"
  },
  {
    "id": "18",
    "info": "eighteen"
  },
  {
    "id": "19",
    "info": "nineteen"
  },
  {
    "id": "20",
    "info": "twenty"
  },
  {
    "id": "21",
    "info": "twenty one"
  },
  {
    "id": "22",
    "info": "twenty two"
  },
  {
    "id": "23",
    "info": "twenty three"
  },
  {
    "id": "24",
    "info": "twenty four"
  },
  {
    "id": "25",
    "info": "twenty five"
  },
  {
    "id": "26",
    "info": "twenty six"
  },
  {
    "id": "27",
    "info": "twenty seven"
  },
  {
    "id": "28",
    "info": "twenty eight"
  },
  {
    "id": "29",
    "info": "twenty nine"
  },
  {
    "id": "30",
    "info": "thirty"
  },
  {
    "id": "31",
    "info": "thirtyone"
  },
  {
    "id": "32",
    "info": "thirtytwo"
  },
  {
    "id": "33",
    "info": "thirtythree"
  },
  {
    "id": "34",
    "info": "thirtyfour"
  },
  {
    "id": "35",
    "info": "thirtyfive"
  },
  {
    "id": "36",
    "info": "thirtysix"
  },
  {
    "id": "37",
    "info": "thirtyseven"
  },
  {
    "id": "35",
    "info": "thirtyfive"
  },
  {
    "id": "36",
    "info": "thirtysix"
  },
  {
    "id": "37",
    "info": "thirtyseven"
  },
  {
    "id": "1",
    "info": "one"
  },
  {
    "id": "2",
    "info": "two"
  },
  {
    "id": "3",
    "info": "three"
  },
  {
    "id": "4",
    "info": "four"
  },
  {
    "id": "5",
    "info": "five"
  },
  {
    "id": "6",
    "info": "six"
  },
  {
    "id": "7",
    "info": "seven"
  },
  {
    "id": "8",
    "info": "eight"
  },
  {
    "id": "9",
    "info": "none"
  },
  {
    "id": "10",
    "info": "ten"
  },
  {
    "id": "11",
    "info": "eleven"
  },
  {
    "id": "12",
    "info": "twelve"
  },
  {
    "id": "13",
    "info": "thirteen"
  },
  {
    "id": "14",
    "info": "fourteen"
  },
  {
    "id": "15",
    "info": "fifteen"
  },
  {
    "id": "16",
    "info": "sixteen"
  },
  {
    "id": "17",
    "info": "seventeen"
  },
  {
    "id": "18",
    "info": "eighteen"
  },
  {
    "id": "19",
    "info": "nineteen"
  },
  {
    "id": "20",
    "info": "twenty"
  },
  {
    "id": "21",
    "info": "twenty one"
  },
  {
    "id": "22",
    "info": "twenty two"
  },
  {
    "id": "23",
    "info": "twenty three"
  },
  {
    "id": "24",
    "info": "twenty four"
  },
  {
    "id": "25",
    "info": "twenty five"
  },
  {
    "id": "26",
    "info": "twenty six"
  },
  {
    "id": "27",
    "info": "twenty seven"
  },
  {
    "id": "28",
    "info": "twenty eight"
  },
  {
    "id": "29",
    "info": "twenty nine"
  },
  {
    "id": "30",
    "info": "thirty"
  },
  {
    "id": "31",
    "info": "thirtyone"
  },
  {
    "id": "32",
    "info": "thirtytwo"
  },
  {
    "id": "33",
    "info": "thirtythree"
  },
  {
    "id": "34",
    "info": "thirtyfour"
  },
  {
    "id": "35",
    "info": "thirtyfive"
  },
  {
    "id": "36",
    "info": "thirtysix"
  },
  {
    "id": "37",
    "info": "thirtyseven"
  },
  {
    "id": "35",
    "info": "thirtyfive"
  },
  {
    "id": "36",
    "info": "thirtysix"
  },
  {
    "id": "37",
    "info": "thirtyseven"
  },
  {
    "id": "1",
    "info": "one"
  },
  {
    "id": "2",
    "info": "two"
  },
  {
    "id": "3",
    "info": "three"
  },
  {
    "id": "4",
    "info": "four"
  },
  {
    "id": "5",
    "info": "five"
  },
  {
    "id": "6",
    "info": "six"
  },
  {
    "id": "7",
    "info": "seven"
  },
  {
    "id": "8",
    "info": "eight"
  },
  {
    "id": "9",
    "info": "none"
  },
  {
    "id": "10",
    "info": "ten"
  },
  {
    "id": "11",
    "info": "eleven"
  },
  {
    "id": "12",
    "info": "twelve"
  },
  {
    "id": "13",
    "info": "thirteen"
  },
  {
    "id": "14",
    "info": "fourteen"
  },
  {
    "id": "15",
    "info": "fifteen"
  },
  {
    "id": "16",
    "info": "sixteen"
  },
  {
    "id": "17",
    "info": "seventeen"
  },
  {
    "id": "18",
    "info": "eighteen"
  },
  {
    "id": "19",
    "info": "nineteen"
  },
  {
    "id": "20",
    "info": "twenty"
  },
  {
    "id": "21",
    "info": "twenty one"
  },
  {
    "id": "22",
    "info": "twenty two"
  },
  {
    "id": "23",
    "info": "twenty three"
  },
  {
    "id": "24",
    "info": "twenty four"
  },
  {
    "id": "25",
    "info": "twenty five"
  },
  {
    "id": "26",
    "info": "twenty six"
  },
  {
    "id": "27",
    "info": "twenty seven"
  },
  {
    "id": "28",
    "info": "twenty eight"
  },
  {
    "id": "29",
    "info": "twenty nine"
  },
  {
    "id": "30",
    "info": "thirty"
  },
  {
    "id": "31",
    "info": "thirtyone"
  },
  {
    "id": "32",
    "info": "thirtytwo"
  },
  {
    "id": "33",
    "info": "thirtythree"
  },
  {
    "id": "34",
    "info": "thirtyfour"
  },
  {
    "id": "35",
    "info": "thirtyfive"
  },
  {
    "id": "36",
    "info": "thirtysix"
  },
  {
    "id": "37",
    "info": "thirtyseven"
  },
  {
    "id": "35",
    "info": "thirtyfive"
  },
  {
    "id": "36",
    "info": "thirtysix"
  },
  {
    "id": "37",
    "info": "thirtyseven"
  },
  {
    "id": "1",
    "info": "one"
  },
  {
    "id": "2",
    "info": "two"
  },
  {
    "id": "3",
    "info": "three"
  },
  {
    "id": "4",
    "info": "four"
  },
  {
    "id": "5",
    "info": "five"
  },
  {
    "id": "6",
    "info": "six"
  },
  {
    "id": "7",
    "info": "seven"
  },
  {
    "id": "8",
    "info": "eight"
  },
  {
    "id": "9",
    "info": "none"
  },
  {
    "id": "10",
    "info": "ten"
  },
  {
    "id": "11",
    "info": "eleven"
  },
  {
    "id": "12",
    "info": "twelve"
  },
  {
    "id": "13",
    "info": "thirteen"
  },
  {
    "id": "14",
    "info": "fourteen"
  },
  {
    "id": "15",
    "info": "fifteen"
  },
  {
    "id": "16",
    "info": "sixteen"
  },
  {
    "id": "17",
    "info": "seventeen"
  },
  {
    "id": "18",
    "info": "eighteen"
  },
  {
    "id": "19",
    "info": "nineteen"
  },
  {
    "id": "20",
    "info": "twenty"
  },
  {
    "id": "21",
    "info": "twenty one"
  },
  {
    "id": "22",
    "info": "twenty two"
  },
  {
    "id": "23",
    "info": "twenty three"
  },
  {
    "id": "24",
    "info": "twenty four"
  },
  {
    "id": "25",
    "info": "twenty five"
  },
  {
    "id": "26",
    "info": "twenty six"
  },
  {
    "id": "27",
    "info": "twenty seven"
  },
  {
    "id": "28",
    "info": "twenty eight"
  },
  {
    "id": "29",
    "info": "twenty nine"
  },
  {
    "id": "30",
    "info": "thirty"
  },
  {
    "id": "31",
    "info": "thirtyone"
  },
  {
    "id": "32",
    "info": "thirtytwo"
  },
  {
    "id": "33",
    "info": "thirtythree"
  },
  {
    "id": "34",
    "info": "thirtyfour"
  },
  {
    "id": "35",
    "info": "thirtyfive"
  },
  {
    "id": "36",
    "info": "thirtysix"
  },
  {
    "id": "37",
    "info": "thirtyseven"
  },
  {
    "id": "35",
    "info": "thirtyfive"
  },
  {
    "id": "36",
    "info": "thirtysix"
  },
  {
    "id": "37",
    "info": "thirtyseven"
  },
  {
    "id": "1",
    "info": "one"
  },
  {
    "id": "2",
    "info": "two"
  },
  {
    "id": "3",
    "info": "three"
  },
  {
    "id": "4",
    "info": "four"
  },
  {
    "id": "5",
    "info": "five"
  },
  {
    "id": "6",
    "info": "six"
  },
  {
    "id": "7",
    "info": "seven"
  },
  {
    "id": "8",
    "info": "eight"
  },
  {
    "id": "9",
    "info": "none"
  },
  {
    "id": "10",
    "info": "ten"
  },
  {
    "id": "11",
    "info": "eleven"
  },
  {
    "id": "12",
    "info": "twelve"
  },
  {
    "id": "13",
    "info": "thirteen"
  },
  {
    "id": "14",
    "info": "fourteen"
  },
  {
    "id": "15",
    "info": "fifteen"
  },
  {
    "id": "16",
    "info": "sixteen"
  },
  {
    "id": "17",
    "info": "seventeen"
  },
  {
    "id": "18",
    "info": "eighteen"
  },
  {
    "id": "19",
    "info": "nineteen"
  },
  {
    "id": "20",
    "info": "twenty"
  },
  {
    "id": "21",
    "info": "twenty one"
  },
  {
    "id": "22",
    "info": "twenty two"
  },
  {
    "id": "23",
    "info": "twenty three"
  },
  {
    "id": "24",
    "info": "twenty four"
  },
  {
    "id": "25",
    "info": "twenty five"
  },
  {
    "id": "26",
    "info": "twenty six"
  },
  {
    "id": "27",
    "info": "twenty seven"
  },
  {
    "id": "28",
    "info": "twenty eight"
  },
  {
    "id": "29",
    "info": "twenty nine"
  },
  {
    "id": "30",
    "info": "thirty"
  },
  {
    "id": "31",
    "info": "thirtyone"
  },
  {
    "id": "32",
    "info": "thirtytwo"
  },
  {
    "id": "33",
    "info": "thirtythree"
  },
  {
    "id": "34",
    "info": "thirtyfour"
  },
  {
    "id": "35",
    "info": "thirtyfive"
  },
  {
    "id": "36",
    "info": "thirtysix"
  },
  {
    "id": "37",
    "info": "thirtyseven"
  },
  {
    "id": "35",
    "info": "thirtyfive"
  },
  {
    "id": "36",
    "info": "thirtysix"
  },
  {
    "id": "37",
    "info": "thirtyseven"
  },
  {
    "id": "1",
    "info": "one"
  },
  {
    "id": "2",
    "info": "two"
  },
  {
    "id": "3",
    "info": "three"
  },
  {
    "id": "4",
    "info": "four"
  },
  {
    "id": "5",
    "info": "five"
  },
  {
    "id": "6",
    "info": "six"
  },
  {
    "id": "7",
    "info": "seven"
  },
  {
    "id": "8",
    "info": "eight"
  },
  {
    "id": "9",
    "info": "none"
  },
  {
    "id": "10",
    "info": "ten"
  },
  {
    "id": "11",
    "info": "eleven"
  },
  {
    "id": "12",
    "info": "twelve"
  },
  {
    "id": "13",
    "info": "thirteen"
  },
  {
    "id": "14",
    "info": "fourteen"
  },
  {
    "id": "15",
    "info": "fifteen"
  },
  {
    "id": "16",
    "info": "sixteen"
  },
  {
    "id": "17",
    "info": "seventeen"
  },
  {
    "id": "18",
    "info": "eighteen"
  },
  {
    "id": "19",
    "info": "nineteen"
  },
  {
    "id": "20",
    "info": "twenty"
  },
  {
    "id": "21",
    "info": "twenty one"
  },
  {
    "id": "22",
    "info": "twenty two"
  },
  {
    "id": "23",
    "info": "twenty three"
  },
  {
    "id": "24",
    "info": "twenty four"
  },
  {
    "id": "25",
    "info": "twenty five"
  },
  {
    "id": "26",
    "info": "twenty six"
  },
  {
    "id": "27",
    "info": "twenty seven"
  },
  {
    "id": "28",
    "info": "twenty eight"
  },
  {
    "id": "29",
    "info": "twenty nine"
  },
  {
    "id": "30",
    "info": "thirty"
  },
  {
    "id": "31",
    "info": "thirtyone"
  },
  {
    "id": "32",
    "info": "thirtytwo"
  },
  {
    "id": "33",
    "info": "thirtythree"
  },
  {
    "id": "34",
    "info": "thirtyfour"
  },
  {
    "id": "35",
    "info": "thirtyfive"
  },
  {
    "id": "36",
    "info": "thirtysix"
  },
  {
    "id": "37",
    "info": "thirtyseven"
  },
  {
    "id": "35",
    "info": "thirtyfive"
  },
  {
    "id": "36",
    "info": "thirtysix"
  },
  {
    "id": "37",
    "info": "thirtyseven"
  },
  {
    "id": "1",
    "info": "one"
  },
  {
    "id": "2",
    "info": "two"
  },
  {
    "id": "3",
    "info": "three"
  },
  {
    "id": "4",
    "info": "four"
  },
  {
    "id": "5",
    "info": "five"
  },
  {
    "id": "6",
    "info": "six"
  },
  {
    "id": "7",
    "info": "seven"
  },
  {
    "id": "8",
    "info": "eight"
  },
  {
    "id": "9",
    "info": "none"
  },
  {
    "id": "10",
    "info": "ten"
  },
  {
    "id": "11",
    "info": "eleven"
  },
  {
    "id": "12",
    "info": "twelve"
  },
  {
    "id": "13",
    "info": "thirteen"
  },
  {
    "id": "14",
    "info": "fourteen"
  },
  {
    "id": "15",
    "info": "fifteen"
  },
  {
    "id": "16",
    "info": "sixteen"
  },
  {
    "id": "17",
    "info": "seventeen"
  },
  {
    "id": "18",
    "info": "eighteen"
  },
  {
    "id": "19",
    "info": "nineteen"
  },
  {
    "id": "20",
    "info": "twenty"
  },
  {
    "id": "21",
    "info": "twenty one"
  },
  {
    "id": "22",
    "info": "twenty two"
  },
  {
    "id": "23",
    "info": "twenty three"
  },
  {
    "id": "24",
    "info": "twenty four"
  },
  {
    "id": "25",
    "info": "twenty five"
  },
  {
    "id": "26",
    "info": "twenty six"
  },
  {
    "id": "27",
    "info": "twenty seven"
  },
  {
    "id": "28",
    "info": "twenty eight"
  },
  {
    "id": "29",
    "info": "twenty nine"
  },
  {
    "id": "30",
    "info": "thirty"
  },
  {
    "id": "31",
    "info": "thirtyone"
  },
  {
    "id": "32",
    "info": "thirtytwo"
  },
  {
    "id": "33",
    "info": "thirtythree"
  },
  {
    "id": "34",
    "info": "thirtyfour"
  },
  {
    "id": "35",
    "info": "thirtyfive"
  },
  {
    "id": "36",
    "info": "thirtysix"
  },
  {
    "id": "37",
    "info": "thirtyseven"
  },
  {
    "id": "35",
    "info": "thirtyfive"
  },
  {
    "id": "36",
    "info": "thirtysix"
  },
  {
    "id": "37",
    "info": "thirtyseven"
  }
]
